[
  {
    "type": "flight-offer",
    "id": "1",
    "source": "GDS",
    "instantTicketingRequired": false,
    "nonHomogeneous": false,
    "oneWay": false,
    "isUpsellOffer": false,
    "lastTicketingDate": "2026-01-04",
    "lastTicketingDateTime": "2026-01-04",
    "numberOfBookableSeats": 9,
    "itineraries": [
      {
        "duration": "PT6H2M",
        "segments": [
          {
            "departure": {
              "iataCode": "RDU",
              "terminal": "2",
              "at": "2026-01-19T10:20:00"
            },
            "arrival": {
              "iataCode": "IAD",
              "at": "2026-01-19T11:30:00"
            },
            "carrierCode": "UA",
            "number": "2163",
            "aircraft": {
              "code": "738"
            },
            "operating": {
              "carrierCode": "UA"
            },
            "duration": "PT1H10M",
            "id": "1",
            "numberOfStops": 0,
            "blacklistedInEU": false
          },
          {
            "departure": {
              "iataCode": "IAD",
              "at": "2026-01-19T13:20:00"
            },
            "arrival": {
              "iataCode": "MIA",
              "at": "2026-01-19T16:22:00"
            },
            "carrierCode": "UA",
            "number": "723",
            "aircraft": {
              "code": "739"
            },
            "operating": {
              "carrierCode": "UA"
            },
            "duration": "PT3H2M",
            "id": "2",
            "numberOfStops": 0,
            "blacklistedInEU": false
          }
        ]
      }
    ],
    "price": {
      "currency": "USD",
      "total": "138.31",
      "base": "105.21",
      "fees": [
        {
          "amount": "0.00",
          "type": "SUPPLIER"
        },
        {
          "amount": "0.00",
          "type": "TICKETING"
        }
      ],
      "grandTotal": "138.31"
    },
    "pricingOptions": {
      "fareType": [
        "PUBLISHED"
      ],
      "includedCheckedBagsOnly": false
    },
    "validatingAirlineCodes": [
      "UA"
    ],
    "travelerPricings": [
      {
        "travelerId": "1",
        "fareOption": "STANDARD",
        "travelerType": "ADULT",
        "price": {
          "currency": "USD",
          "total": "138.31",
          "base": "105.21"
        },
        "fareDetailsBySegment": [
          {
            "segmentId": "1",
            "cabin": "ECONOMY",
            "fareBasis": "KAA7PFDN",
            "brandedFare": "ECONOMY",
            "brandedFareLabel": "ECONOMY",
            "class": "K",
            "includedCheckedBags": {
              "quantity": 0
            },
            "includedCabinBags": {
              "quantity": 1
            },
            "amenities": [
              {
                "description": "CHECKED BAG FIRST",
                "isChargeable": true,
                "amenityType": "BAGGAGE",
                "amenityProvider": {
                  "name": "BrandedFare"
                }
              },
              {
                "description": "SECOND BAG",
                "isChargeable": true,
                "amenityType": "BAGGAGE",
                "amenityProvider": {
                  "name": "BrandedFare"
                }
              },
              {
                "description": "PRE RESERVED SEAT ASSIGNMENT",
                "isChargeable": false,
                "amenityType": "PRE_RESERVED_SEAT",
                "amenityProvider": {
                  "name": "BrandedFare"
                }
              },
              {
                "description": "PRIORITY BOARDING",
                "isChargeable": true,
                "amenityType": "TRAVEL_SERVICES",
                "amenityProvider": {
                  "name": "BrandedFare"
                }
              },
              {
                "description": "ECONOMY TO ECONOMY PLUS",
                "isChargeable": true,
                "amenityType": "UPGRADES",
                "amenityProvider": {
                  "name": "BrandedFare"
                }
              },
              {
                "description": "MILEAGE ACCRUAL",
                "isChargeable": false,
                "amenityType": "BRANDED_FARES",
                "amenityProvider": {
                  "name": "BrandedFare"
                }
              }
            ]
          },
          {
            "segmentId": "2",
            "cabin": "ECONOMY",
            "fareBasis": "KAA7PFDN",
            "brandedFare": "ECONOMY",
            "brandedFareLabel": "ECONOMY",
            "class": "K",
            "includedCheckedBags": {
              "quantity": 0
            },
            "includedCabinBags": {
              "quantity": 1
            },
            "amenities": [
              {
                "description": "CHECKED BAG FIRST",
                "isChargeable": true,
                "amenityType": "BAGGAGE",
                "amenityProvider": {
                  "name": "BrandedFare"
                }
              },
              {
                "description": "SECOND BAG",
                "isChargeable": true,
                "amenityType": "BAGGAGE",
                "amenityProvider": {
                  "name": "BrandedFare"
                }
              },
              {
                "description": "PRE RESERVED SEAT ASSIGNMENT",
                "isChargeable": false,
                "amenityType": "PRE_RESERVED_SEAT",
                "amenityProvider": {
                  "name": "BrandedFare"
                }
              },
              {
                "description": "PRIORITY BOARDING",
                "isChargeable": true,
                "amenityType": "TRAVEL_SERVICES",
                "amenityProvider": {
                  "name": "BrandedFare"
                }
              },
              {
                "description": "ECONOMY TO ECONOMY PLUS",
                "isChargeable": true,
                "amenityType": "UPGRADES",
                "amenityProvider": {
                  "name": "BrandedFare"
                }
              },
              {
                "description": "MILEAGE ACCRUAL",
                "isChargeable": false,
                "amenityType": "BRANDED_FARES",
                "amenityProvider": {
                  "name": "BrandedFare"
                }
              }
            ]
          }
        ]
      }
    ]
  },
  {
    "type": "flight-offer",
    "id": "2",
    "source": "GDS",
    "instantTicketingRequired": false,
    "nonHomogeneous": false,
    "oneWay": false,
    "isUpsellOffer": false,
    "lastTicketingDate": "2026-01-04",
    "lastTicketingDateTime": "2026-01-04",
    "numberOfBookableSeats": 9,
    "itineraries": [
      {
        "duration": "PT7H5M",
        "segments": [
          {
            "departure": {
              "iataCode": "RDU",
              "terminal": "2",
              "at": "2026-01-19T15:15:00"
            },
            "arrival": {
              "iataCode": "EWR",
              "terminal": "C",
              "at": "2026-01-19T17:05:00"
            },
            "carrierCode": "UA",
            "number": "2175",
            "aircraft": {
              "code": "7M9"
            },
            "operating": {
              "carrierCode": "UA"
            },
            "duration": "PT1H50M",
            "id": "5",
            "numberOfStops": 0,
            "blacklistedInEU": false
          },
          {
            "departure": {
              "iataCode": "EWR",
              "terminal": "C",
              "at": "2026-01-19T18:59:00"
            },
            "arrival": {
              "iataCode": "MIA",
              "at": "2026-01-19T22:20:00"
            },
            "carrierCode": "UA",
            "number": "1128",
            "aircraft": {
              "code": "7M8"
            },
            "operating": {
              "carrierCode": "UA"
            },
            "duration": "PT3H21M",
            "id": "6",
            "numberOfStops": 0,
            "blacklistedInEU": false
          }
        ]
      }
    ],
    "price": {
      "currency": "USD",
      "total": "138.31",
      "base": "105.21",
      "fees": [
        {
          "amount": "0.00",
          "type": "SUPPLIER"
        },
        {
          "amount": "0.00",
          "type": "TICKETING"
        }
      ],
      "grandTotal": "138.31"
    },
    "pricingOptions": {
      "fareType": [
        "PUBLISHED"
      ],
      "includedCheckedBagsOnly": false
    },
    "validatingAirlineCodes": [
      "UA"
    ],
    "travelerPricings": [
      {
        "travelerId": "1",
        "fareOption": "STANDARD",
        "travelerType": "ADULT",
        "price": {
          "currency": "USD",
          "total": "138.31",
          "base": "105.21"
        },
        "fareDetailsBySegment": [
          {
            "segmentId": "5",
            "cabin": "ECONOMY",
            "fareBasis": "KAA7PFDN",
            "brandedFare": "ECONOMY",
            "brandedFareLabel": "ECONOMY",
            "class": "K",
            "includedCheckedBags": {
              "quantity": 0
            },
            "includedCabinBags": {
              "quantity": 1
            },
            "amenities": [
              {
                "description": "CHECKED BAG FIRST",
                "isChargeable": true,
                "amenityType": "BAGGAGE",
                "amenityProvider": {
                  "name": "BrandedFare"
                }
              },
              {
                "description": "SECOND BAG",
                "isChargeable": true,
                "amenityType": "BAGGAGE",
                "amenityProvider": {
                  "name": "BrandedFare"
                }
              },
              {
                "description": "PRE RESERVED SEAT ASSIGNMENT",
                "isChargeable": false,
                "amenityType": "PRE_RESERVED_SEAT",
                "amenityProvider": {
                  "name": "BrandedFare"
                }
              },
              {
                "description": "PRIORITY BOARDING",
                "isChargeable": true,
                "amenityType": "TRAVEL_SERVICES",
                "amenityProvider": {
                  "name": "BrandedFare"
                }
              },
              {
                "description": "ECONOMY TO ECONOMY PLUS",
                "isChargeable": true,
                "amenityType": "UPGRADES",
                "amenityProvider": {
                  "name": "BrandedFare"
                }
              },
              {
                "description": "MILEAGE ACCRUAL",
                "isChargeable": false,
                "amenityType": "BRANDED_FARES",
                "amenityProvider": {
                  "name": "BrandedFare"
                }
              }
            ]
          },
          {
            "segmentId": "6",
            "cabin": "ECONOMY",
            "fareBasis": "KAA7PFDN",
            "brandedFare": "ECONOMY",
            "brandedFareLabel": "ECONOMY",
            "class": "K",
            "includedCheckedBags": {
              "quantity": 0
            },
            "includedCabinBags": {
              "quantity": 1
            },
            "amenities": [
              {
                "description": "CHECKED BAG FIRST",
                "isChargeable": true,
                "amenityType": "BAGGAGE",
                "amenityProvider": {
                  "name": "BrandedFare"
                }
              },
              {
                "description": "SECOND BAG",
                "isChargeable": true,
                "amenityType": "BAGGAGE",
                "amenityProvider": {
                  "name": "BrandedFare"
                }
              },
              {
                "description": "PRE RESERVED SEAT ASSIGNMENT",
                "isChargeable": false,
                "amenityType": "PRE_RESERVED_SEAT",
                "amenityProvider": {
                  "name": "BrandedFare"
                }
              },
              {
                "description": "PRIORITY BOARDING",
                "isChargeable": true,
                "amenityType": "TRAVEL_SERVICES",
                "amenityProvider": {
                  "name": "BrandedFare"
                }
              },
              {
                "description": "ECONOMY TO ECONOMY PLUS",
                "isChargeable": true,
                "amenityType": "UPGRADES",
                "amenityProvider": {
                  "name": "BrandedFare"
                }
              },
              {
                "description": "MILEAGE ACCRUAL",
                "isChargeable": false,
                "amenityType": "BRANDED_FARES",
                "amenityProvider": {
                  "name": "BrandedFare"
                }
              }
            ]
          }
        ]
      }
    ]
  },
  {
    "type": "flight-offer",
    "id": "3",
    "source": "GDS",
    "instantTicketingRequired": false,
    "nonHomogeneous": false,
    "oneWay": false,
    "isUpsellOffer": false,
    "lastTicketingDate": "2026-01-04",
    "lastTicketingDateTime": "2026-01-04",
    "numberOfBookableSeats": 9,
    "itineraries": [
      {
        "duration": "PT8H44M",
        "segments": [
          {
            "departure": {
              "iataCode": "RDU",
              "terminal": "2",
              "at": "2026-01-19T15:15:00"
            },
            "arrival": {
              "iataCode": "EWR",
              "terminal": "C",
              "at": "2026-01-19T17:05:00"
            },
            "carrierCode": "UA",
            "number": "2175",
            "aircraft": {
              "code": "7M9"
            },
            "operating": {
              "carrierCode": "UA"
            },
            "duration": "PT1H50M",
            "id": "7",
            "numberOfStops": 0,
            "blacklistedInEU": false
          },
          {
            "departure": {
              "iataCode": "EWR",
              "terminal": "C",
              "at": "2026-01-19T20:38:00"
            },
            "arrival": {
              "iataCode": "MIA",
              "at": "2026-01-19T23:59:00"
            },
            "carrierCode": "UA",
            "number": "448",
            "aircraft": {
              "code": "7M9"
            },
            "operating": {
              "carrierCode": "UA"
            },
            "duration": "PT3H21M",
            "id": "8",
            "numberOfStops": 0,
            "blacklistedInEU": false
          }
        ]
      }
    ],
    "price": {
      "currency": "USD",
      "total": "138.31",
      "base": "105.21",
      "fees": [
        {
          "amount": "0.00",
          "type": "SUPPLIER"
        },
        {
          "amount": "0.00",
          "type": "TICKETING"
        }
      ],
      "grandTotal": "138.31"
    },
    "pricingOptions": {
      "fareType": [
        "PUBLISHED"
      ],
      "includedCheckedBagsOnly": false
    },
    "validatingAirlineCodes": [
      "UA"
    ],
    "travelerPricings": [
      {
        "travelerId": "1",
        "fareOption": "STANDARD",
        "travelerType": "ADULT",
        "price": {
          "currency": "USD",
          "total": "138.31",
          "base": "105.21"
        },
        "fareDetailsBySegment": [
          {
            "segmentId": "7",
            "cabin": "ECONOMY",
            "fareBasis": "KAA7PFDN",
            "brandedFare": "ECONOMY",
            "brandedFareLabel": "ECONOMY",
            "class": "K",
            "includedCheckedBags": {
              "quantity": 0
            },
            "includedCabinBags": {
              "quantity": 1
            },
            "amenities": [
              {
                "description": "CHECKED BAG FIRST",
                "isChargeable": true,
                "amenityType": "BAGGAGE",
                "amenityProvider": {
                  "name": "BrandedFare"
                }
              },
              {
                "description": "SECOND BAG",
                "isChargeable": true,
                "amenityType": "BAGGAGE",
                "amenityProvider": {
                  "name": "BrandedFare"
                }
              },
              {
                "description": "PRE RESERVED SEAT ASSIGNMENT",
                "isChargeable": false,
                "amenityType": "PRE_RESERVED_SEAT",
                "amenityProvider": {
                  "name": "BrandedFare"
                }
              },
              {
                "description": "PRIORITY BOARDING",
                "isChargeable": true,
                "amenityType": "TRAVEL_SERVICES",
                "amenityProvider": {
                  "name": "BrandedFare"
                }
              },
              {
                "description": "ECONOMY TO ECONOMY PLUS",
                "isChargeable": true,
                "amenityType": "UPGRADES",
                "amenityProvider": {
                  "name": "BrandedFare"
                }
              },
              {
                "description": "MILEAGE ACCRUAL",
                "isChargeable": false,
                "amenityType": "BRANDED_FARES",
                "amenityProvider": {
                  "name": "BrandedFare"
                }
              }
            ]
          },
          {
            "segmentId": "8",
            "cabin": "ECONOMY",
            "fareBasis": "KAA7PFDN",
            "brandedFare": "ECONOMY",
            "brandedFareLabel": "ECONOMY",
            "class": "K",
            "includedCheckedBags": {
              "quantity": 0
            },
            "includedCabinBags": {
              "quantity": 1
            },
            "amenities": [
              {
                "description": "CHECKED BAG FIRST",
                "isChargeable": true,
                "amenityType": "BAGGAGE",
                "amenityProvider": {
                  "name": "BrandedFare"
                }
              },
              {
                "description": "SECOND BAG",
                "isChargeable": true,
                "amenityType": "BAGGAGE",
                "amenityProvider": {
                  "name": "BrandedFare"
                }
              },
              {
                "description": "PRE RESERVED SEAT ASSIGNMENT",
                "isChargeable": false,
                "amenityType": "PRE_RESERVED_SEAT",
                "amenityProvider": {
                  "name": "BrandedFare"
                }
              },
              {
                "description": "PRIORITY BOARDING",
                "isChargeable": true,
                "amenityType": "TRAVEL_SERVICES",
                "amenityProvider": {
                  "name": "BrandedFare"
                }
              },
              {
                "description": "ECONOMY TO ECONOMY PLUS",
                "isChargeable": true,
                "amenityType": "UPGRADES",
                "amenityProvider": {
                  "name": "BrandedFare"
                }
              },
              {
                "description": "MILEAGE ACCRUAL",
                "isChargeable": false,
                "amenityType": "BRANDED_FARES",
                "amenityProvider": {
                  "name": "BrandedFare"
                }
              }
            ]
          }
        ]
      }
    ]
  },
  {
    "type": "flight-offer",
    "id": "4",
    "source": "GDS",
    "instantTicketingRequired": false,
    "nonHomogeneous": false,
    "oneWay": false,
    "isUpsellOffer": false,
    "lastTicketingDate": "2026-01-04",
    "lastTicketingDateTime": "2026-01-04",
    "numberOfBookableSeats": 9,
    "itineraries": [
      {
        "duration": "PT8H50M",
        "segments": [
          {
            "departure": {
              "iataCode": "RDU",
              "terminal": "2",
              "at": "2026-01-19T06:15:00"
            },
            "arrival": {
              "iataCode": "ORD",
              "terminal": "1",
              "at": "2026-01-19T07:44:00"
            },
            "carrierCode": "UA",
            "number": "2638",
            "aircraft": {
              "code": "73G"
            },
            "operating": {
              "carrierCode": "UA"
            },
            "duration": "PT2H29M",
            "id": "9",
            "numberOfStops": 0,
            "blacklistedInEU": false
          },
          {
            "departure": {
              "iataCode": "ORD",
              "terminal": "1",
              "at": "2026-01-19T10:35:00"
            },
            "arrival": {
              "iataCode": "MIA",
              "at": "2026-01-19T15:05:00"
            },
            "carrierCode": "UA",
            "number": "1857",
            "aircraft": {
              "code": "32Q"
            },
            "operating": {
              "carrierCode": "UA"
            },
            "duration": "PT3H30M",
            "id": "10",
            "numberOfStops": 0,
            "blacklistedInEU": false
          }
        ]
      }
    ],
    "price": {
      "currency": "USD",
      "total": "138.31",
      "base": "105.21",
      "fees": [
        {
          "amount": "0.00",
          "type": "SUPPLIER"
        },
        {
          "amount": "0.00",
          "type": "TICKETING"
        }
      ],
      "grandTotal": "138.31"
    },
    "pricingOptions": {
      "fareType": [
        "PUBLISHED"
      ],
      "includedCheckedBagsOnly": false
    },
    "validatingAirlineCodes": [
      "UA"
    ],
    "travelerPricings": [
      {
        "travelerId": "1",
        "fareOption": "STANDARD",
        "travelerType": "ADULT",
        "price": {
          "currency": "USD",
          "total": "138.31",
          "base": "105.21"
        },
        "fareDetailsBySegment": [
          {
            "segmentId": "9",
            "cabin": "ECONOMY",
            "fareBasis": "KAA7PFDN",
            "brandedFare": "ECONOMY",
            "brandedFareLabel": "ECONOMY",
            "class": "K",
            "includedCheckedBags": {
              "quantity": 0
            },
            "includedCabinBags": {
              "quantity": 1
            },
            "amenities": [
              {
                "description": "CHECKED BAG FIRST",
                "isChargeable": true,
                "amenityType": "BAGGAGE",
                "amenityProvider": {
                  "name": "BrandedFare"
                }
              },
              {
                "description": "SECOND BAG",
                "isChargeable": true,
                "amenityType": "BAGGAGE",
                "amenityProvider": {
                  "name": "BrandedFare"
                }
              },
              {
                "description": "PRE RESERVED SEAT ASSIGNMENT",
                "isChargeable": false,
                "amenityType": "PRE_RESERVED_SEAT",
                "amenityProvider": {
                  "name": "BrandedFare"
                }
              },
              {
                "description": "PRIORITY BOARDING",
                "isChargeable": true,
                "amenityType": "TRAVEL_SERVICES",
                "amenityProvider": {
                  "name": "BrandedFare"
                }
              },
              {
                "description": "ECONOMY TO ECONOMY PLUS",
                "isChargeable": true,
                "amenityType": "UPGRADES",
                "amenityProvider": {
                  "name": "BrandedFare"
                }
              },
              {
                "description": "MILEAGE ACCRUAL",
                "isChargeable": false,
                "amenityType": "BRANDED_FARES",
                "amenityProvider": {
                  "name": "BrandedFare"
                }
              }
            ]
          },
          {
            "segmentId": "10",
            "cabin": "ECONOMY",
            "fareBasis": "KAA7PFDN",
            "brandedFare": "ECONOMY",
            "brandedFareLabel": "ECONOMY",
            "class": "K",
            "includedCheckedBags": {
              "quantity": 0
            },
            "includedCabinBags": {
              "quantity": 1
            },
            "amenities": [
              {
                "description": "CHECKED BAG FIRST",
                "isChargeable": true,
                "amenityType": "BAGGAGE",
                "amenityProvider": {
                  "name": "BrandedFare"
                }
              },
              {
                "description": "SECOND BAG",
                "isChargeable": true,
                "amenityType": "BAGGAGE",
                "amenityProvider": {
                  "name": "BrandedFare"
                }
              },
              {
                "description": "PRE RESERVED SEAT ASSIGNMENT",
                "isChargeable": false,
                "amenityType": "PRE_RESERVED_SEAT",
                "amenityProvider": {
                  "name": "BrandedFare"
                }
              },
              {
                "description": "PRIORITY BOARDING",
                "isChargeable": true,
                "amenityType": "TRAVEL_SERVICES",
                "amenityProvider": {
                  "name": "BrandedFare"
                }
              },
              {
                "description": "ECONOMY TO ECONOMY PLUS",
                "isChargeable": true,
                "amenityType": "UPGRADES",
                "amenityProvider": {
                  "name": "BrandedFare"
                }
              },
              {
                "description": "MILEAGE ACCRUAL",
                "isChargeable": false,
                "amenityType": "BRANDED_FARES",
                "amenityProvider": {
                  "name": "BrandedFare"
                }
              }
            ]
          }
        ]
      }
    ]
  },
  {
    "type": "flight-offer",
    "id": "5",
    "source": "GDS",
    "instantTicketingRequired": false,
    "nonHomogeneous": false,
    "oneWay": false,
    "isUpsellOffer": false,
    "lastTicketingDate": "2026-01-04",
    "lastTicketingDateTime": "2026-01-04",
    "numberOfBookableSeats": 9,
    "itineraries": [
      {
        "duration": "PT9H4M",
        "segments": [
          {
            "departure": {
              "iataCode": "RDU",
              "terminal": "2",
              "at": "2026-01-19T11:18:00"
            },
            "arrival": {
              "iataCode": "EWR",
              "terminal": "C",
              "at": "2026-01-19T13:00:00"
            },
            "carrierCode": "UA",
            "number": "2289",
            "aircraft": {
              "code": "319"
            },
            "operating": {
              "carrierCode": "UA"
            },
            "duration": "PT1H42M",
            "id": "3",
            "numberOfStops": 0,
            "blacklistedInEU": false
          },
          {
            "departure": {
              "iataCode": "EWR",
              "terminal": "C",
              "at": "2026-01-19T16:58:00"
            },
            "arrival": {
              "iataCode": "MIA",
              "at": "2026-01-19T20:22:00"
            },
            "carrierCode": "UA",
            "number": "2612",
            "aircraft": {
              "code": "739"
            },
            "operating": {
              "carrierCode": "UA"
            },
            "duration": "PT3H24M",
            "id": "4",
            "numberOfStops": 0,
            "blacklistedInEU": false
          }
        ]
      }
    ],
    "price": {
      "currency": "USD",
      "total": "138.31",
      "base": "105.21",
      "fees": [
        {
          "amount": "0.00",
          "type": "SUPPLIER"
        },
        {
          "amount": "0.00",
          "type": "TICKETING"
        }
      ],
      "grandTotal": "138.31"
    },
    "pricingOptions": {
      "fareType": [
        "PUBLISHED"
      ],
      "includedCheckedBagsOnly": false
    },
    "validatingAirlineCodes": [
      "UA"
    ],
    "travelerPricings": [
      {
        "travelerId": "1",
        "fareOption": "STANDARD",
        "travelerType": "ADULT",
        "price": {
          "currency": "USD",
          "total": "138.31",
          "base": "105.21"
        },
        "fareDetailsBySegment": [
          {
            "segmentId": "3",
            "cabin": "ECONOMY",
            "fareBasis": "KAA7PFDN",
            "brandedFare": "ECONOMY",
            "brandedFareLabel": "ECONOMY",
            "class": "K",
            "includedCheckedBags": {
              "quantity": 0
            },
            "includedCabinBags": {
              "quantity": 1
            },
            "amenities": [
              {
                "description": "CHECKED BAG FIRST",
                "isChargeable": true,
                "amenityType": "BAGGAGE",
                "amenityProvider": {
                  "name": "BrandedFare"
                }
              },
              {
                "description": "SECOND BAG",
                "isChargeable": true,
                "amenityType": "BAGGAGE",
                "amenityProvider": {
                  "name": "BrandedFare"
                }
              },
              {
                "description": "PRE RESERVED SEAT ASSIGNMENT",
                "isChargeable": false,
                "amenityType": "PRE_RESERVED_SEAT",
                "amenityProvider": {
                  "name": "BrandedFare"
                }
              },
              {
                "description": "PRIORITY BOARDING",
                "isChargeable": true,
                "amenityType": "TRAVEL_SERVICES",
                "amenityProvider": {
                  "name": "BrandedFare"
                }
              },
              {
                "description": "ECONOMY TO ECONOMY PLUS",
                "isChargeable": true,
                "amenityType": "UPGRADES",
                "amenityProvider": {
                  "name": "BrandedFare"
                }
              },
              {
                "description": "MILEAGE ACCRUAL",
                "isChargeable": false,
                "amenityType": "BRANDED_FARES",
                "amenityProvider": {
                  "name": "BrandedFare"
                }
              }
            ]
          },
          {
            "segmentId": "4",
            "cabin": "ECONOMY",
            "fareBasis": "KAA7PFDN",
            "brandedFare": "ECONOMY",
            "brandedFareLabel": "ECONOMY",
            "class": "K",
            "includedCheckedBags": {
              "quantity": 0
            },
            "includedCabinBags": {
              "quantity": 1
            },
            "amenities": [
              {
                "description": "CHECKED BAG FIRST",
                "isChargeable": true,
                "amenityType": "BAGGAGE",
                "amenityProvider": {
                  "name": "BrandedFare"
                }
              },
              {
                "description": "SECOND BAG",
                "isChargeable": true,
                "amenityType": "BAGGAGE",
                "amenityProvider": {
                  "name": "BrandedFare"
                }
              },
              {
                "description": "PRE RESERVED SEAT ASSIGNMENT",
                "isChargeable": false,
                "amenityType": "PRE_RESERVED_SEAT",
                "amenityProvider": {
                  "name": "BrandedFare"
                }
              },
              {
                "description": "PRIORITY BOARDING",
                "isChargeable": true,
                "amenityType": "TRAVEL_SERVICES",
                "amenityProvider": {
                  "name": "BrandedFare"
                }
              },
              {
                "description": "ECONOMY TO ECONOMY PLUS",
                "isChargeable": true,
                "amenityType": "UPGRADES",
                "amenityProvider": {
                  "name": "BrandedFare"
                }
              },
              {
                "description": "MILEAGE ACCRUAL",
                "isChargeable": false,
                "amenityType": "BRANDED_FARES",
                "amenityProvider": {
                  "name": "BrandedFare"
                }
              }
            ]
          }
        ]
      }
    ]
  }
]